sanic_pw/__init__.py
sanic_pw/models.py
sanic_pw/orm.py
sanic_pw-0.2.0.dist-info/METADATA
sanic_pw-0.2.0.dist-info/RECORD
sanic_pw-0.2.0.dist-info/WHEEL
sanic_pw-0.2.0.dist-info/top_level.txt
