Metadata-Version: 2.1
Name: sanic-pw
Version: 0.2.0
Summary: Peewee ORM integration for Sanic framework
Home-page: https://github.com/Relrin/sanic-pw
Author: Valeryi Savich
Author-email: Relrin78@gmail.com
License: BSD
Keywords: sanic,peewee,migrations,migrate,signals
Platform: Any
Classifier: Intended Audience :: Developers
Classifier: License :: OSI Approved :: BSD License
Classifier: Natural Language :: English
Classifier: Natural Language :: Russian
Classifier: Operating System :: OS Independent
Classifier: Programming Language :: Python :: 3
Classifier: Topic :: Software Development :: Libraries :: Python Modules
Classifier: Topic :: Software Development :: Testing
Classifier: Topic :: Utilities
Requires-Dist: peewee (==3.3.4)
Requires-Dist: cached-property (==1.4.2)
Requires-Dist: peewee-migrate (==1.0.0)
